{
  "main": {
    "id": "849a12390bbf82a9",
    "type": "split",
    "children": [
      {
        "id": "bb065d9f856113fb",
        "type": "tabs",
        "children": [
          {
            "id": "629c7d6da1fecfa0",
            "type": "leaf",
            "state": {
              "type": "markdown",
              "state": {
                "file": "GitをAndroidで使う方法.md",
                "mode": "source",
                "source": false
              },
              "icon": "lucide-file",
              "title": "GitをAndroidで使う方法"
            }
          },
          {
            "id": "f51ea1b4abed4995",
            "type": "leaf",
            "state": {
              "type": "markdown",
              "state": {
                "file": "自己紹介.md",
                "mode": "source",
                "source": false
              },
              "icon": "lucide-file",
              "title": "自己紹介"
            }
          }
        ],
        "currentTab": 1
      }
    ],
    "direction": "vertical"
  },
  "left": {
    "id": "0ca9567475d06a65",
    "type": "split",
    "children": [
      {
        "id": "3dd627c3a8144d5e",
        "type": "tabs",
        "children": [
          {
            "id": "18521a48c8daa9de",
            "type": "leaf",
            "state": {
              "type": "file-explorer",
              "state": {
                "sortOrder": "alphabetical"
              },
              "icon": "lucide-folder-closed",
              "title": "ファイルエクスプローラ"
            }
          },
          {
            "id": "0c41896200992ea5",
            "type": "leaf",
            "state": {
              "type": "search",
              "state": {
                "query": "",
                "matchingCase": false,
                "explainSearch": false,
                "collapseAll": false,
                "extraContext": false,
                "sortOrder": "alphabetical"
              },
              "icon": "lucide-search",
              "title": "検索"
            }
          },
          {
            "id": "d9480869034711da",
            "type": "leaf",
            "state": {
              "type": "bookmarks",
              "state": {},
              "icon": "lucide-bookmark",
              "title": "ブックマーク"
            }
          }
        ]
      }
    ],
    "direction": "horizontal",
    "width": 300
  },
  "right": {
    "id": "ffc0a20ae8a3f542",
    "type": "split",
    "children": [
      {
        "id": "0267a922edfc913c",
        "type": "tabs",
        "children": [
          {
            "id": "3fbe7410accfea27",
            "type": "leaf",
            "state": {
              "type": "backlink",
              "state": {
                "file": "自己紹介.md",
                "collapseAll": false,
                "extraContext": false,
                "sortOrder": "alphabetical",
                "showSearch": false,
                "searchQuery": "",
                "backlinkCollapsed": false,
                "unlinkedCollapsed": true
              },
              "icon": "links-coming-in",
              "title": "自己紹介へのバックリンク"
            }
          },
          {
            "id": "44be0589694ac0f8",
            "type": "leaf",
            "state": {
              "type": "outgoing-link",
              "state": {
                "file": "自己紹介.md",
                "linksCollapsed": false,
                "unlinkedCollapsed": true
              },
              "icon": "links-going-out",
              "title": "自己紹介からのアウトゴーイングリンク"
            }
          },
          {
            "id": "dc26c72153c5c3b0",
            "type": "leaf",
            "state": {
              "type": "tag",
              "state": {
                "sortOrder": "frequency",
                "useHierarchy": true
              },
              "icon": "lucide-tags",
              "title": "タグ"
            }
          },
          {
            "id": "15021cbe4def1d06",
            "type": "leaf",
            "state": {
              "type": "outline",
              "state": {
                "file": "自己紹介.md"
              },
              "icon": "lucide-list",
              "title": "自己紹介のアウトライン"
            }
          }
        ]
      }
    ],
    "direction": "horizontal",
    "width": 300,
    "collapsed": true
  },
  "left-ribbon": {
    "hiddenItems": {
      "obsidian-git:Open Git source control": false,
      "switcher:クイックスイッチャーを開く": false,
      "graph:グラフビューを開く": false,
      "canvas:新規キャンバスを作成": false,
      "daily-notes:今日のデイリーノートを開く": false,
      "templates:テンプレートを挿入": false,
      "command-palette:コマンドパレットを開く": false
    }
  },
  "active": "f51ea1b4abed4995",
  "lastOpenFiles": [
    "GitをAndroidで使う方法.md",
    "自己紹介.md"
  ]
}